data_transform_taaleks/__init__.py
data_transform_taaleks/function.py
data_transform_taaleks-0.1.0.dist-info/METADATA
data_transform_taaleks-0.1.0.dist-info/WHEEL
data_transform_taaleks-0.1.0.dist-info/RECORD
