Metadata-Version: 2.1
Name: data_transform_taaleks
Version: 0.1.0
Summary: 
Author: TadasAlek
Author-email: tadasalek@gmail.com
Requires-Python: >=3.12,<4.0
Classifier: Programming Language :: Python :: 3
Classifier: Programming Language :: Python :: 3.12
Requires-Dist: numpy (>=2.1.0,<3.0.0)
